codex-python-types/__init__.py
codex-python-types/types.py
codex_python_types/__init__.py
codex_python_types/types.py
codex_python_types-0.0.3.dist-info/METADATA
codex_python_types-0.0.3.dist-info/WHEEL
codex_python_types-0.0.3.dist-info/top_level.txt
codex_python_types-0.0.3.dist-info/RECORD
