Metadata-Version: 2.1
Name: codex-python-types
Version: 0.0.3
Requires-Dist: annotated-types ==0.6.0
Requires-Dist: pydantic ==2.6.0
Requires-Dist: pydantic-core ==2.16.1
Requires-Dist: typing-extensions ==4.9.0
